SlashPaginator/__init__.py
SlashPaginator/slashpaginator.py
SlashPaginator-0.0.3.dist-info/LICENSE
SlashPaginator-0.0.3.dist-info/METADATA
SlashPaginator-0.0.3.dist-info/WHEEL
SlashPaginator-0.0.3.dist-info/top_level.txt
SlashPaginator-0.0.3.dist-info/RECORD
